{"noiseKey":{"private":{"type":"Buffer","data":"2BDw8O+TkEq/xJ4ILMkSjlJcUNy0cO3+HhwVHJPZdG4="},"public":{"type":"Buffer","data":"PY4JoJoPh2ERSiQT6CdMMIk0mAbVUu+joCJM6YPlXWs="}},"pairingEphemeralKeyPair":{"private":{"type":"Buffer","data":"iNANUhvhZKVBlG/zbh2/NghGHYTXhMsWWaZULR8VGlc="},"public":{"type":"Buffer","data":"UPO6BtwGfcC9bGNPOWFk1r0yB1v7/LqNTBhbqQbZhxk="}},"signedIdentityKey":{"private":{"type":"Buffer","data":"iAVvx2CKcf12BCvqcQYvUlu6lRVI57DD6NkVoXcOyU8="},"public":{"type":"Buffer","data":"tvqNx+UiH87nD3fYKH1WwbJ1yc+AwHTSW/ClU77uxRk="}},"signedPreKey":{"keyPair":{"private":{"type":"Buffer","data":"uOk8qUrb56Msud5xDaPJSEc+g/yxS/wJOSvbt/O2zWg="},"public":{"type":"Buffer","data":"bcUkAutcWhazr4FgzI2RNEfOT2HgSN7LRnCz3zQG8nQ="}},"signature":{"type":"Buffer","data":"tEOYWCqNJwDHaaRMzeKo15qNdjY2gJPprduWAxAoZDbQFkW50t7Vs+M1W6IqGYlM8B5w1czB2kCzon0sgyZngA=="},"keyId":1},"registrationId":11,"advSecretKey":"R86O5yXuw9LbKr296pclSrMWCmYvne06m0afO657Gx4=","processedHistoryMessages":[{"key":{"remoteJid":"93786198402@s.whatsapp.net","fromMe":true,"id":"3ABF209A42E7D572F00A"},"messageTimestamp":1754293342},{"key":{"remoteJid":"93786198402@s.whatsapp.net","fromMe":true,"id":"3AB31ECE00FD83F072D0"},"messageTimestamp":1754293345},{"key":{"remoteJid":"93786198402@s.whatsapp.net","fromMe":true,"id":"3ADEF3997FB1BE7DAA6B"},"messageTimestamp":1754293354},{"key":{"remoteJid":"93786198402@s.whatsapp.net","fromMe":true,"id":"3A9F8E5D2CA785456FF3"},"messageTimestamp":1754293363},{"key":{"remoteJid":"93786198402@s.whatsapp.net","fromMe":true,"id":"3A14647110F89FDC92AD"},"messageTimestamp":1754293369},{"key":{"remoteJid":"93786198402@s.whatsapp.net","fromMe":true,"id":"3A5AD493A67DFC219683"},"messageTimestamp":1754293374}],"nextPreKeyId":31,"firstUnuploadedPreKeyId":31,"accountSyncCounter":1,"accountSettings":{"unarchiveChats":false},"registered":true,"pairingCode":"WBJ18C8M","me":{"id":"93786198402:8@s.whatsapp.net","lid":"201558755119108:8@lid","name":"‏𓍼𓆰ᥫ𝕶ོ͢𝙷𝐀𝐋𝐢𝙳ོ͢𓍼"},"account":{"details":"CL3do4kJEMjIwcQGGAEgACgA","accountSignatureKey":"BuGlfqKZwX3hN1Oo32LKvulETCyQjxVSpvqtaGX9vGw=","accountSignature":"uBxANwHKHgiHg2c5hSbRgO/KQFD2AqrQZJmrtoOYULf2CpTaA32CsjZH6gxCipcFT5MBNpVRYSBtLEKKjPE3gA==","deviceSignature":"PDgLewOwfDWkjK9WSAdPid4tLaCUWMpu0/IbhnsKZzhojqUTcnx4zDfeE/o62aoj7iyZgakXR01ZKZoDUr21jQ=="},"signalIdentities":[{"identifier":{"name":"93786198402:8@s.whatsapp.net","deviceId":0},"identifierKey":{"type":"Buffer","data":"BQbhpX6imcF94TdTqN9iyr7pREwskI8VUqb6rWhl/bxs"}}],"platform":"iphone","routingInfo":{"type":"Buffer","data":"CAUICA=="},"lastAccountSyncTimestamp":1754293333,"lastPropHash":"nm3Bb","myAppStateKeyId":"AAAAAMVD"}