{"noiseKey":{"private":{"type":"Buffer","data":"6OFkxVxeu/6mxiCOabo79PTRhcf5dcVjzZ/yNbb4VX0="},"public":{"type":"Buffer","data":"uhsrMSC/sIZrvMrI7aolqZoRzcDO5gAs4IUYDzkUFUE="}},"pairingEphemeralKeyPair":{"private":{"type":"Buffer","data":"cI2ZE2I0ovJnXI+RueeA/MAn8obXOvVFEEIxyLik6kA="},"public":{"type":"Buffer","data":"yIwu4ZTY4lRTg/m6izTKEW7LNJequsbumk/GToyglm0="}},"signedIdentityKey":{"private":{"type":"Buffer","data":"WPV1jgWSTPaJX//FzQpvMtA2dL8guJvLA5m5tOOPJ2Q="},"public":{"type":"Buffer","data":"PM2lrv/BcaF3x6AVrjx9tMGL+qczv45FoF2oyPE4qnQ="}},"signedPreKey":{"keyPair":{"private":{"type":"Buffer","data":"AMmAyCWkpoOJcMnH+y56ydtoxgR3Ut9aSeQZlY2nFFY="},"public":{"type":"Buffer","data":"G9zYd/niYtFA0up7/XGMVLy81jlECjEDEtYaKk6QT0I="}},"signature":{"type":"Buffer","data":"KHi65o2hKIw0LSjtcgtJ7ach57YoLqceEfmhiy2zzGNyrFW/Fh4uwZXKlBw9oEUAv2/mvw3KgsgNG+duQcA2iA=="},"keyId":1},"registrationId":244,"advSecretKey":"/wiQGR7KgcY+djXmcWVAvwQtgjHXYhpN9DhfmQAD0jY=","processedHistoryMessages":[{"key":{"remoteJid":"94776017681@s.whatsapp.net","fromMe":true,"id":"9B0383233A79D5BDABB974F46222669C"},"messageTimestamp":1753934965},{"key":{"remoteJid":"94776017681@s.whatsapp.net","fromMe":true,"id":"039C83E320F10AF412BB3C970A9472A5"},"messageTimestamp":1753934968},{"key":{"remoteJid":"94776017681@s.whatsapp.net","fromMe":true,"id":"52912D4B28DA53C4EF4C40CD7B5F7704"},"messageTimestamp":1753935036},{"key":{"remoteJid":"94776017681@s.whatsapp.net","fromMe":true,"id":"FB91779AD025F8AA0E94D6AC75143C3A"},"messageTimestamp":1753935095},{"key":{"remoteJid":"94776017681@s.whatsapp.net","fromMe":true,"id":"184B5CF782E93A211253AF1280C84BA8"},"messageTimestamp":1753935136},{"key":{"remoteJid":"94776017681@s.whatsapp.net","fromMe":true,"id":"28B07610540BD3FEE587B842A5D11A7A"},"messageTimestamp":1753935168},{"key":{"remoteJid":"94776017681@s.whatsapp.net","fromMe":true,"id":"033A386E41215AE381B7F61976807D9B"},"messageTimestamp":1753935196},{"key":{"remoteJid":"94776017681@s.whatsapp.net","fromMe":true,"id":"EF960AE3DB762F6A97944C0A2934C23D"},"messageTimestamp":1753935215},{"key":{"remoteJid":"94776017681@s.whatsapp.net","fromMe":true,"id":"ECD7C9ABC48FFCD4A8ED89AE16291C55"},"messageTimestamp":1753935239},{"key":{"remoteJid":"94776017681@s.whatsapp.net","fromMe":true,"id":"2E13171199BC27532111F3707D81A06B"},"messageTimestamp":1753935256},{"key":{"remoteJid":"94776017681@s.whatsapp.net","fromMe":true,"id":"B1DCB564EEE35EAD4FD9BDC370E2419B"},"messageTimestamp":1753935280},{"key":{"remoteJid":"94776017681@s.whatsapp.net","fromMe":true,"id":"7FCC9F527C06C3056F4AE85488276D92"},"messageTimestamp":1753935303},{"key":{"remoteJid":"94776017681@s.whatsapp.net","fromMe":true,"id":"F2B5AE55280E4663F02B9714735E977C"},"messageTimestamp":1753935326},{"key":{"remoteJid":"94776017681@s.whatsapp.net","fromMe":true,"id":"55E1DDC23AE8C799393A661280297D06"},"messageTimestamp":1753935347},{"key":{"remoteJid":"94776017681@s.whatsapp.net","fromMe":true,"id":"F104E2C319853D87E65576FFDE66F973"},"messageTimestamp":1753935375},{"key":{"remoteJid":"94776017681@s.whatsapp.net","fromMe":true,"id":"4F125E19A4E4B3700325A52BA30BCE72"},"messageTimestamp":1753935418},{"key":{"remoteJid":"94776017681@s.whatsapp.net","fromMe":true,"id":"3C1B154FA645380C3C95310A3B3D6C9E"},"messageTimestamp":1753935453},{"key":{"remoteJid":"94776017681@s.whatsapp.net","fromMe":true,"id":"2A385DC9D1B51A5228AB3E809D424A54"},"messageTimestamp":1753935477},{"key":{"remoteJid":"94776017681@s.whatsapp.net","fromMe":true,"id":"3AE86B2B0DEA6A2F45FD8ACBDEA21FA8"},"messageTimestamp":1753935515},{"key":{"remoteJid":"94776017681@s.whatsapp.net","fromMe":true,"id":"4E718A0F5094A958629B08EEF8D2FBA8"},"messageTimestamp":1753935550},{"key":{"remoteJid":"94776017681@s.whatsapp.net","fromMe":true,"id":"D76CA5EA4E2713A6C53BC45236909135"},"messageTimestamp":1753935586},{"key":{"remoteJid":"94776017681@s.whatsapp.net","fromMe":true,"id":"EF34B7D2DDED94F6202345EA6861EDF2"},"messageTimestamp":1753935624},{"key":{"remoteJid":"94776017681@s.whatsapp.net","fromMe":true,"id":"7A1B7B4CCA2C3A5DFDA50599D04D6839"},"messageTimestamp":1753935639}],"nextPreKeyId":114,"firstUnuploadedPreKeyId":114,"accountSyncCounter":1,"accountSettings":{"unarchiveChats":false},"registered":true,"pairingCode":"BLHXANC5","me":{"id":"94776017681:17@s.whatsapp.net","lid":"125743841448019:17@lid","name":"94776017681"},"account":{"details":"CNG1i84BEN7Yq8QGGAcgACgA","accountSignatureKey":"t2Dwi82WGy45cxe37b1yF0IABu5m7VHqlzByXPmIVwM=","accountSignature":"4SYFqI5faUgfIiQ4+tdGnFgPbJsliqvBy1EPl4/k4Zkf2W73yKXOTj2X3g/CshEakrJ/JtTlxga+e3+NYz8gDA==","deviceSignature":"QO78u4fBG95Bn6s+ToQdG3INX+ckGw0OLr0Qn58pgRwDrX9X/2PytjbGEq8TRdXtsgZFmxJwpff2Ywl5l0yQhQ=="},"signalIdentities":[{"identifier":{"name":"94776017681:17@s.whatsapp.net","deviceId":0},"identifierKey":{"type":"Buffer","data":"Bbdg8IvNlhsuOXMXt+29chdCAAbuZu1R6pcwclz5iFcD"}}],"platform":"android","routingInfo":{"type":"Buffer","data":"CBIICA=="},"lastAccountSyncTimestamp":1753936866,"lastPropHash":"1K4hH4","myAppStateKeyId":"AAAAAEul"}